[
  {
    "url": "https://chromeexperiments.com",
    "title": "100,000 Stars Interactive Galaxy",
    "tags": "Science, Space"
  },
  {
    "url": "https://withgoogle.com",
    "title": "Quick, Draw! Neural Network Game",
    "tags": "Games, AI"
  },
  {
    "url": "https://vectorizer.com",
    "title": "Free Raster to Vector Converter",
    "tags": "Design, Utilities"
  },
  {
    "url": "https://linerider.com",
    "title": "Line Rider Classic Browser Game",
    "tags": "Nostalgia, Games"
  }
]
